{
    "created_time": "2024-12-07T20:25:47Z",
    "files": [
        {
            "attachment_folder": "",
            "created_time": "2024-12-07T20:25:47Z",
            "id": "146",
            "modified_time": "2024-12-07T20:25:47Z",
            "name": "Conversiones.md",
            "signature": "2656046397925928779",
            "tags": [
            ]
        },
        {
            "attachment_folder": "",
            "created_time": "2024-12-07T20:25:47Z",
            "id": "148",
            "modified_time": "2024-12-07T20:25:47Z",
            "name": "Metodo Punto Fijo.md",
            "signature": "17553765278764281675",
            "tags": [
            ]
        },
        {
            "attachment_folder": "",
            "created_time": "2024-12-07T20:25:47Z",
            "id": "150",
            "modified_time": "2024-12-07T20:25:47Z",
            "name": "punto_flotante.md",
            "signature": "8684218634938396491",
            "tags": [
            ]
        }
    ],
    "folders": [
    ],
    "id": "149",
    "modified_time": "2024-12-07T20:25:47Z",
    "signature": "10695324624475172683",
    "version": 3
}
