{
    "created_time": "2024-09-05T17:23:38Z",
    "files": [
        {
            "attachment_folder": "",
            "created_time": "2024-09-05T17:23:38Z",
            "id": "222",
            "modified_time": "2024-09-05T17:23:38Z",
            "name": "1. Que hacemos.md",
            "signature": "2726370276867172634",
            "tags": [
            ]
        },
        {
            "attachment_folder": "",
            "created_time": "2024-09-05T17:23:38Z",
            "id": "223",
            "modified_time": "2024-09-05T17:23:38Z",
            "name": "2. Que implica investigar.md",
            "signature": "5547390799305107738",
            "tags": [
            ]
        },
        {
            "attachment_folder": "",
            "created_time": "2024-09-05T17:23:38Z",
            "id": "224",
            "modified_time": "2024-09-05T17:23:38Z",
            "name": "3. Imagen y Video.md",
            "signature": "5164340687857641754",
            "tags": [
            ]
        },
        {
            "attachment_folder": "",
            "created_time": "2024-09-05T17:23:38Z",
            "id": "225",
            "modified_time": "2024-09-05T17:23:38Z",
            "name": "4. Datos y Tareas.md",
            "signature": "7813336289643194650",
            "tags": [
            ]
        }
    ],
    "folders": [
    ],
    "id": "221",
    "modified_time": "2024-09-05T17:23:38Z",
    "signature": "7021673508029196570",
    "version": 3
}
