{
    "created_time": "2024-12-20T15:46:54Z",
    "files": [
        {
            "attachment_folder": "",
            "created_time": "2024-12-20T15:46:54Z",
            "id": "509",
            "modified_time": "2024-12-20T15:46:54Z",
            "name": "1. Introduccion.md",
            "signature": "4637314231751250286",
            "tags": [
            ]
        },
        {
            "attachment_folder": "",
            "created_time": "2024-12-20T15:46:54Z",
            "id": "511",
            "modified_time": "2024-12-20T15:46:54Z",
            "name": "2. Modelos de redes.md",
            "signature": "10166261997380145518",
            "tags": [
            ]
        },
        {
            "attachment_folder": "",
            "created_time": "2024-12-20T15:46:54Z",
            "id": "513",
            "modified_time": "2024-12-20T15:46:54Z",
            "name": "3. Capa de acceso a la red.md",
            "signature": "12521189073968533870",
            "tags": [
            ]
        }
    ],
    "folders": [
        {
            "name": "4. Capa de Internet"
        }
    ],
    "id": "528",
    "modified_time": "2024-12-20T15:46:54Z",
    "signature": "17523581326645891438",
    "version": 3
}
